hypernova/__init__.py
hypernova/build_c_code.py
hypernova/hypernova_c.pyd
hypernova/propagation.py
hypernova/examples/__init__.py
hypernova/examples/basic_orbit_and_plot.py
hypernova/solvers/__init__.py
hypernova/solvers/solver_configurations.py
hypernova/solvers/solver_solution.py
hypernova/visualization/__init__.py
hypernova/visualization/mpl_plotters.py
hypernova_orbit-0.2.0.dist-info/LICENSE
hypernova_orbit-0.2.0.dist-info/METADATA
hypernova_orbit-0.2.0.dist-info/WHEEL
hypernova_orbit-0.2.0.dist-info/top_level.txt
hypernova_orbit-0.2.0.dist-info/RECORD
