Metadata-Version: 2.1
Name: hypernova-orbit
Version: 0.2.0
Summary: Orbit propagation and analysis tool.
Home-page: https://github.com/spacesys-finch/hypernova/
Author: Mingde Yin
License: LGPLv3
Platform: UNKNOWN
Classifier: Development Status :: 3 - Alpha
Classifier: Programming Language :: Python :: 3
Classifier: License :: OSI Approved :: MIT License
Classifier: Operating System :: OS Independent
Classifier: Programming Language :: C
Classifier: Topic :: Scientific/Engineering :: Physics
Classifier: Intended Audience :: Science/Research
Requires-Python: >=3.6
License-File: LICENSE
Requires-Dist: cffi (>=1.15.0)
Requires-Dist: numpy
Requires-Dist: matplotlib
